pyproc/__init__.py
pyproc/process.py
python_pyproc-1.0.0a0.dist-info/LICENSE
python_pyproc-1.0.0a0.dist-info/METADATA
python_pyproc-1.0.0a0.dist-info/WHEEL
python_pyproc-1.0.0a0.dist-info/top_level.txt
python_pyproc-1.0.0a0.dist-info/RECORD
