Metadata-Version: 2.1
Name: python-pyproc
Version: 1.0.0a0
Summary: Turn a function into a process with a simple decorator.
Author-email: Abdallah Gamal <body20002.test@gmail.com>
License: MIT License
Project-URL: Homepage, https://github.com/body20002/pyproc
Project-URL: repository, https://github.com/body20002/pyproc
Project-URL: Bug Tracker, https://github.com/body20002/pyproc/issues
Keywords: python,process,async_process
Classifier: Intended Audience :: Developers
Classifier: Operating System :: OS Independent
Classifier: License :: OSI Approved :: MIT License
Classifier: Programming Language :: Python
Classifier: Programming Language :: Python :: 3
Classifier: Programming Language :: Python :: 3.10
Classifier: Programming Language :: Python :: 3.11
Requires-Python: >=3.10
License-File: LICENSE
Provides-Extra: dev
Requires-Dist: black ; extra == 'dev'
Requires-Dist: isort ; extra == 'dev'
